README.md
setup.py
finance_scraping/__init__.py
finance_scraping/aws.py
finance_scraping/config.py
finance_scraping/finance_scraping_dag.py
finance_scraping/loading.py
finance_scraping/main.py
finance_scraping/mappings.py
finance_scraping/parsing_html.py
finance_scraping/scraping.py
finance_scraping/sql_commands.py
finance_scraping/utils.py
finance_scraping.egg-info/PKG-INFO
finance_scraping.egg-info/SOURCES.txt
finance_scraping.egg-info/dependency_links.txt
finance_scraping.egg-info/entry_points.txt
finance_scraping.egg-info/requires.txt
finance_scraping.egg-info/top_level.txt
finance_scraping/scripts/backfill_load.sh
finance_scraping/scripts/backfill_transform.sh
finance_scraping/scripts/configure.sh
finance_scraping/scripts/terraform_build.sh
finance_scraping/scripts/terraform_configure.sh
finance_scraping/scripts/terraform_nuke.sh